easyfirebase/__init__.py
easyfirebase/apps.py
easyfirebase/fields.py
easyfirebase/storage.py
easyfirebase-2.0.0.dist-info/LICENSE
easyfirebase-2.0.0.dist-info/METADATA
easyfirebase-2.0.0.dist-info/WHEEL
easyfirebase-2.0.0.dist-info/top_level.txt
easyfirebase-2.0.0.dist-info/RECORD
