Metadata-Version: 2.1
Name: easyfirebase
Version: 2.0.0
Summary: A Firebase-django integration package where your files are uploaded to Firebase and the rest of the work is done by the package.
Author-email: "Md. Rubel H." <mail.rubel.me@gmail.com>
Project-URL: Homepage, https://github.com/rubelliumm/EasyFirebase
Project-URL: Issues, https://github.com/rubelliumm/EasyFirebase/issues
Classifier: License :: OSI Approved :: Apache Software License
Classifier: Programming Language :: Python :: 3
Classifier: Programming Language :: Python :: 3.8
Classifier: Programming Language :: Python :: 3.9
Classifier: Programming Language :: Python :: 3.10
Requires-Python: >=3.8
License-File: LICENSE
Requires-Dist: Django >=3.0
Requires-Dist: firebase-admin ==6.5.0
Requires-Dist: pillow ==10.2.0
